datamate/__init__.py
datamate/context.py
datamate/diff.py
datamate/directory.py
datamate/io.py
datamate/metadata.py
datamate/namespaces.py
datamate/utils.py
datamate/version.py
datamate-1.0.0.dist-info/METADATA
datamate-1.0.0.dist-info/WHEEL
datamate-1.0.0.dist-info/top_level.txt
datamate-1.0.0.dist-info/RECORD
