Metadata-Version: 2.2
Name: datamate
Version: 1.0.0
Summary: A data organization and compilation system.
License: MIT License
Project-URL: Homepage, https://github.com/flyvis/datamate
Project-URL: Bug Tracker, https://github.com/flyvis/datamate/issues
Classifier: Intended Audience :: Developers
Classifier: Intended Audience :: Science/Research
Classifier: Topic :: Scientific/Engineering
Classifier: License :: OSI Approved :: MIT License
Classifier: Programming Language :: Python :: 3
Classifier: Development Status :: 3 - Alpha
Requires-Python: <3.13,>=3.9
Requires-Dist: numpy
Requires-Dist: pandas
Requires-Dist: typing_extensions
Requires-Dist: h5py>=3.6.0
Requires-Dist: ruamel.yaml
Requires-Dist: PyYAML
Provides-Extra: dev
Requires-Dist: pre-commit; extra == "dev"
Requires-Dist: jupyter; extra == "dev"
Requires-Dist: setuptools_scm; extra == "dev"
Requires-Dist: pytest; extra == "dev"
Requires-Dist: ruff; extra == "dev"
Requires-Dist: pytest-cov; extra == "dev"
Provides-Extra: docs
Requires-Dist: mkdocs; extra == "docs"
Requires-Dist: mkdocs-material; extra == "docs"
Requires-Dist: markdown-include; extra == "docs"
Requires-Dist: mkdocs-redirects; extra == "docs"
Requires-Dist: mkdocstrings[python]>=0.18; extra == "docs"
Requires-Dist: nbconvert; extra == "docs"
Requires-Dist: mike; extra == "docs"
Requires-Dist: mkdocs-macros-plugin; extra == "docs"
Requires-Dist: jupyter; extra == "docs"
Requires-Dist: tabulate; extra == "docs"
Requires-Dist: tqdm; extra == "docs"
Requires-Dist: ipywidgets; extra == "docs"
